charbeat-0.2.dist-info/DESCRIPTION.rst
charbeat-0.2.dist-info/METADATA
charbeat-0.2.dist-info/pydist.json
charbeat-0.2.dist-info/RECORD
charbeat-0.2.dist-info/top_level.txt
charbeat-0.2.dist-info/WHEEL
chartbeat/__init__.py
