Metadata-Version: 2.0
Name: charbeat
Version: 0.2
Summary: A charbeat/newsbeat API wrapper.
Home-page: https://github.com/cyberdelia/chartbeat
Author: Timothée Peignier
Author-email: timothee.peignier@tryphon.org
License: UNKNOWN
Platform: UNKNOWN
Classifier: Intended Audience :: Developers
Classifier: License :: OSI Approved :: MIT License
Classifier: Operating System :: OS Independent
Classifier: Programming Language :: Python
Classifier: Topic :: Utilities
Requires-Dist: requests
